{
  "projects": [
    {
      "name": "19 Feb 2020, 4%3A06",
      "clock": {
        "BPM": 82.81020395096539,
        "BPMIsGuessed": true,
        "beatsPerBar": 4,
        "length": 23.185548500000003,
        "lengthIsSet": false,
        "metadataVersion": 2,
        "multiplier": 8,
        "originalBPM": 82.81020395096539
      },
      "tracks": [],
      "id": 1
    },
    {
      "name": "19 Feb 2020, 4%3A06",
      "clock": {
        "BPM": 82.81020395096539,
        "BPMIsGuessed": true,
        "beatsPerBar": 4,
        "length": 23.185548500000003,
        "lengthIsSet": false,
        "metadataVersion": 2,
        "multiplier": 8,
        "originalBPM": 82.81020395096539
      },
      "tracks": [],
      "id": 2
    },
    {
      "name": "19 Feb 2020, 4%3A06",
      "clock": {
        "BPM": 82.81020395096539,
        "BPMIsGuessed": true,
        "beatsPerBar": 4,
        "length": 23.185548500000003,
        "lengthIsSet": false,
        "metadataVersion": 2,
        "multiplier": 8,
        "originalBPM": 82.81020395096539
      },
      "tracks": [],
      "id": 3
    }
  ],
  "tracks": [
    {
      "projectId": 1,
      "entityType": 0,
      "entityId": 4,
      "pan": 0,
      "playing": false,
      "reverse": false,
      "scale": 1,
      "synchronize": true,
      "volume": 1,
      "id": 1
    },
    {
      "projectId": 1,
      "entityType": 0,
      "pan": 0,
      "playing": false,
      "reverse": false,
      "scale": 1,
      "synchronize": true,
      "volume": 1,
      "id": 2
    },
    {
      "projectId": 1,
      "entityType": 0,
      "entityId": 1,
      "pan": 0,
      "playing": false,
      "reverse": false,
      "scale": 1,
      "synchronize": true,
      "volume": 1,
      "id": 3
    },
    {
      "projectId": 1,
      "entityType": 0,
      "entityId": 3,
      "pan": 0,
      "playing": false,
      "reverse": false,
      "scale": 1,
      "synchronize": true,
      "volume": 1,
      "id": 4
    },
    {
      "projectId": 1,
      "entityType": 0,
      "entityId": 2,
      "pan": 0,
      "playing": true,
      "reverse": false,
      "scale": 1,
      "synchronize": true,
      "volume": 0.47641730308532715,
      "id": 5
    },
    {
      "projectId": 1,
      "entityType": 0,
      "entityId": 8,
      "pan": 0,
      "playing": false,
      "reverse": false,
      "scale": 1,
      "synchronize": true,
      "volume": 0.8889628648757935,
      "id": 6
    },
    {
      "projectId": 1,
      "entityType": 0,
      "entityId": 5,
      "pan": 0,
      "playing": false,
      "reverse": false,
      "scale": 1,
      "synchronize": true,
      "volume": 1,
      "id": 7
    },
    {
      "projectId": 1,
      "entityType": 0,
      "entityId": 6,
      "pan": 0.43517276644706726,
      "playing": false,
      "reverse": false,
      "scale": 1,
      "synchronize": true,
      "volume": 1,
      "id": 8
    },
    {
      "projectId": 1,
      "entityType": 0,
      "entityId": 7,
      "pan": 0,
      "playing": true,
      "reverse": false,
      "scale": 1,
      "synchronize": true,
      "volume": 1,
      "id": 9
    },
    {
      "projectId": 1,
      "entityType": 0,
      "pan": 0.6121366620063782,
      "playing": false,
      "reverse": false,
      "scale": 1,
      "synchronize": true,
      "volume": 0.11066117882728577,
      "id": 10
    },
    {
      "projectId": 1,
      "entityType": 0,
      "pan": -0.557410478591919,
      "playing": false,
      "reverse": false,
      "scale": 1,
      "synchronize": true,
      "volume": 0.46544572710990906,
      "id": 11
    },
    {
      "projectId": 1,
      "entityType": 0,
      "entityId": 9,
      "pan": 0,
      "playing": true,
      "reverse": false,
      "scale": 1,
      "synchronize": true,
      "volume": 1,
      "id": 12
    },
    {
      "projectId": 2,
      "entityType": 0,
      "entityId": 15,
      "pan": 0,
      "playing": false,
      "reverse": false,
      "scale": 1,
      "synchronize": true,
      "volume": 1,
      "id": 13
    },
    {
      "projectId": 2,
      "entityType": 0,
      "pan": 0,
      "playing": false,
      "reverse": false,
      "scale": 1,
      "synchronize": true,
      "volume": 1,
      "id": 14
    },
    {
      "projectId": 2,
      "entityType": 0,
      "entityId": 13,
      "pan": 0,
      "playing": false,
      "reverse": false,
      "scale": 1,
      "synchronize": true,
      "volume": 1,
      "id": 15
    },
    {
      "projectId": 2,
      "entityType": 0,
      "entityId": 16,
      "pan": 0,
      "playing": false,
      "reverse": false,
      "scale": 1,
      "synchronize": true,
      "volume": 1,
      "id": 16
    },
    {
      "projectId": 2,
      "entityType": 0,
      "entityId": 14,
      "pan": 0,
      "playing": true,
      "reverse": false,
      "scale": 1,
      "synchronize": true,
      "volume": 0.47641730308532715,
      "id": 17
    },
    {
      "projectId": 2,
      "entityType": 0,
      "entityId": 19,
      "pan": 0,
      "playing": false,
      "reverse": false,
      "scale": 1,
      "synchronize": true,
      "volume": 0.8889628648757935,
      "id": 18
    },
    {
      "projectId": 2,
      "entityType": 0,
      "entityId": 17,
      "pan": 0,
      "playing": false,
      "reverse": false,
      "scale": 1,
      "synchronize": true,
      "volume": 1,
      "id": 19
    },
    {
      "projectId": 2,
      "entityType": 0,
      "entityId": 18,
      "pan": 0.43517276644706726,
      "playing": false,
      "reverse": false,
      "scale": 1,
      "synchronize": true,
      "volume": 1,
      "id": 20
    },
    {
      "projectId": 2,
      "entityType": 0,
      "entityId": 20,
      "pan": 0,
      "playing": true,
      "reverse": false,
      "scale": 1,
      "synchronize": true,
      "volume": 1,
      "id": 21
    },
    {
      "projectId": 2,
      "entityType": 0,
      "entityId": 21,
      "pan": 0.6121366620063782,
      "playing": false,
      "reverse": false,
      "scale": 1,
      "synchronize": true,
      "volume": 0.11066117882728577,
      "id": 22
    },
    {
      "projectId": 2,
      "entityType": 0,
      "pan": -0.557410478591919,
      "playing": false,
      "reverse": false,
      "scale": 1,
      "synchronize": true,
      "volume": 0.46544572710990906,
      "id": 23
    },
    {
      "projectId": 2,
      "entityType": 0,
      "entityId": 22,
      "pan": 0,
      "playing": true,
      "reverse": false,
      "scale": 1,
      "synchronize": true,
      "volume": 1,
      "id": 24
    },
    {
      "projectId": 3,
      "entityType": 0,
      "entityId": 28,
      "pan": 0,
      "playing": false,
      "reverse": false,
      "scale": 1,
      "synchronize": true,
      "volume": 1,
      "id": 25
    },
    {
      "projectId": 3,
      "entityType": 0,
      "entityId": 36,
      "pan": 0,
      "playing": false,
      "reverse": false,
      "scale": 1,
      "synchronize": true,
      "volume": 1,
      "id": 26
    },
    {
      "projectId": 3,
      "entityType": 0,
      "entityId": 25,
      "pan": 0,
      "playing": false,
      "reverse": false,
      "scale": 1,
      "synchronize": true,
      "volume": 1,
      "id": 27
    },
    {
      "projectId": 3,
      "entityType": 0,
      "entityId": 27,
      "pan": 0,
      "playing": false,
      "reverse": false,
      "scale": 1,
      "synchronize": true,
      "volume": 1,
      "id": 28
    },
    {
      "projectId": 3,
      "entityType": 0,
      "entityId": 26,
      "pan": 0,
      "playing": true,
      "reverse": false,
      "scale": 1,
      "synchronize": true,
      "volume": 0.47641730308532715,
      "id": 29
    },
    {
      "projectId": 3,
      "entityType": 0,
      "entityId": 32,
      "pan": 0,
      "playing": false,
      "reverse": false,
      "scale": 1,
      "synchronize": true,
      "volume": 0.8889628648757935,
      "id": 30
    },
    {
      "projectId": 3,
      "entityType": 0,
      "entityId": 29,
      "pan": 0,
      "playing": false,
      "reverse": false,
      "scale": 1,
      "synchronize": true,
      "volume": 1,
      "id": 31
    },
    {
      "projectId": 3,
      "entityType": 0,
      "entityId": 30,
      "pan": 0.43517276644706726,
      "playing": false,
      "reverse": false,
      "scale": 1,
      "synchronize": true,
      "volume": 1,
      "id": 32
    },
    {
      "projectId": 3,
      "entityType": 0,
      "entityId": 31,
      "pan": 0,
      "playing": true,
      "reverse": false,
      "scale": 1,
      "synchronize": true,
      "volume": 1,
      "id": 33
    },
    {
      "projectId": 3,
      "entityType": 0,
      "entityId": 33,
      "pan": 0.6121366620063782,
      "playing": false,
      "reverse": false,
      "scale": 1,
      "synchronize": true,
      "volume": 0.11066117882728577,
      "id": 34
    },
    {
      "projectId": 3,
      "entityType": 0,
      "entityId": 34,
      "pan": -0.557410478591919,
      "playing": false,
      "reverse": false,
      "scale": 1,
      "synchronize": true,
      "volume": 0.46544572710990906,
      "id": 35
    },
    {
      "projectId": 3,
      "entityType": 0,
      "entityId": 35,
      "pan": 0,
      "playing": true,
      "reverse": false,
      "scale": 1,
      "synchronize": true,
      "volume": 1,
      "id": 36
    }
  ],
  "loops": [
    {
      "originalProjectId": 1,
      "decay": 0,
      "loopStartTime": 0,
      "originalLoopStartTime": -1,
      "originalScale": 0,
      "filePath": "/home/timfitzgerald/stemmy/stemmy-common/fileStore/p1-2.aiff",
      "source": 2,
      "pngPaths": [],
      "id": 1
    },
    {
      "originalProjectId": 1,
      "decay": 0,
      "loopStartTime": 0,
      "originalLoopStartTime": -1,
      "originalScale": 0,
      "filePath": "/home/timfitzgerald/stemmy/stemmy-common/fileStore/p1-4.aiff",
      "source": 2,
      "pngPaths": [],
      "id": 2
    },
    {
      "originalProjectId": 1,
      "decay": 0,
      "loopStartTime": 0,
      "originalLoopStartTime": -1,
      "originalScale": 0,
      "filePath": "/home/timfitzgerald/stemmy/stemmy-common/fileStore/p1-3.aiff",
      "source": 2,
      "pngPaths": [],
      "id": 3
    },
    {
      "originalProjectId": 1,
      "decay": 0,
      "loopStartTime": 0,
      "originalLoopStartTime": -1,
      "originalScale": 0,
      "filePath": "/home/timfitzgerald/stemmy/stemmy-common/fileStore/p1-0.aiff",
      "source": 2,
      "pngPaths": [],
      "id": 4
    },
    {
      "originalProjectId": 1,
      "decay": 0,
      "loopStartTime": 0,
      "originalLoopStartTime": -1,
      "originalScale": 0,
      "filePath": "/home/timfitzgerald/stemmy/stemmy-common/fileStore/p1-6.aiff",
      "source": 2,
      "pngPaths": [],
      "id": 5
    },
    {
      "originalProjectId": 1,
      "decay": 0,
      "loopStartTime": 0,
      "originalLoopStartTime": -1,
      "originalScale": 0,
      "filePath": "/home/timfitzgerald/stemmy/stemmy-common/fileStore/p1-7.aiff",
      "source": 2,
      "pngPaths": [],
      "id": 6
    },
    {
      "originalProjectId": 1,
      "decay": 0,
      "loopStartTime": 0,
      "originalLoopStartTime": -1,
      "originalScale": 0,
      "filePath": "/home/timfitzgerald/stemmy/stemmy-common/fileStore/p1-8.aiff",
      "source": 2,
      "pngPaths": [],
      "id": 7
    },
    {
      "originalProjectId": 1,
      "decay": 0,
      "loopStartTime": 0,
      "originalLoopStartTime": -1,
      "originalScale": 0,
      "filePath": "/home/timfitzgerald/stemmy/stemmy-common/fileStore/p1-5.aiff",
      "source": 2,
      "pngPaths": [],
      "id": 8
    },
    {
      "originalProjectId": 1,
      "decay": 0,
      "loopStartTime": 0,
      "originalLoopStartTime": -1,
      "originalScale": 0,
      "filePath": "/home/timfitzgerald/stemmy/stemmy-common/fileStore/p1-11.aiff",
      "source": 2,
      "pngPaths": [],
      "id": 9
    },
    {
      "originalProjectId": 1,
      "decay": 0,
      "loopStartTime": 0,
      "originalLoopStartTime": -1,
      "originalScale": 0,
      "filePath": "/home/timfitzgerald/stemmy/stemmy-common/fileStore/p1-9.aiff",
      "source": 2,
      "pngPaths": [],
      "id": 10
    },
    {
      "originalProjectId": 1,
      "decay": 0,
      "loopStartTime": 0,
      "originalLoopStartTime": -1,
      "originalScale": 0,
      "filePath": "/home/timfitzgerald/stemmy/stemmy-common/fileStore/p1-10.aiff",
      "source": 2,
      "pngPaths": [],
      "id": 11
    },
    {
      "originalProjectId": 1,
      "decay": 0,
      "loopStartTime": 0,
      "originalLoopStartTime": -1,
      "originalScale": 0,
      "filePath": "/home/timfitzgerald/stemmy/stemmy-common/fileStore/p1-1.aiff",
      "source": 2,
      "pngPaths": [],
      "id": 12
    },
    {
      "originalProjectId": 2,
      "decay": 0,
      "loopStartTime": 0,
      "originalLoopStartTime": -1,
      "originalScale": 0,
      "filePath": "/home/timfitzgerald/stemmy/stemmy-common/fileStore/p2-2.aiff",
      "source": 2,
      "pngPaths": [],
      "id": 13
    },
    {
      "originalProjectId": 2,
      "decay": 0,
      "loopStartTime": 0,
      "originalLoopStartTime": -1,
      "originalScale": 0,
      "filePath": "/home/timfitzgerald/stemmy/stemmy-common/fileStore/p2-4.aiff",
      "source": 2,
      "pngPaths": [],
      "id": 14
    },
    {
      "originalProjectId": 2,
      "decay": 0,
      "loopStartTime": 0,
      "originalLoopStartTime": -1,
      "originalScale": 0,
      "filePath": "/home/timfitzgerald/stemmy/stemmy-common/fileStore/p2-0.aiff",
      "source": 2,
      "pngPaths": [],
      "id": 15
    },
    {
      "originalProjectId": 2,
      "decay": 0,
      "loopStartTime": 0,
      "originalLoopStartTime": -1,
      "originalScale": 0,
      "filePath": "/home/timfitzgerald/stemmy/stemmy-common/fileStore/p2-3.aiff",
      "source": 2,
      "pngPaths": [],
      "id": 16
    },
    {
      "originalProjectId": 2,
      "decay": 0,
      "loopStartTime": 0,
      "originalLoopStartTime": -1,
      "originalScale": 0,
      "filePath": "/home/timfitzgerald/stemmy/stemmy-common/fileStore/p2-6.aiff",
      "source": 2,
      "pngPaths": [],
      "id": 17
    },
    {
      "originalProjectId": 2,
      "decay": 0,
      "loopStartTime": 0,
      "originalLoopStartTime": -1,
      "originalScale": 0,
      "filePath": "/home/timfitzgerald/stemmy/stemmy-common/fileStore/p2-7.aiff",
      "source": 2,
      "pngPaths": [],
      "id": 18
    },
    {
      "originalProjectId": 2,
      "decay": 0,
      "loopStartTime": 0,
      "originalLoopStartTime": -1,
      "originalScale": 0,
      "filePath": "/home/timfitzgerald/stemmy/stemmy-common/fileStore/p2-5.aiff",
      "source": 2,
      "pngPaths": [],
      "id": 19
    },
    {
      "originalProjectId": 2,
      "decay": 0,
      "loopStartTime": 0,
      "originalLoopStartTime": -1,
      "originalScale": 0,
      "filePath": "/home/timfitzgerald/stemmy/stemmy-common/fileStore/p2-8.aiff",
      "source": 2,
      "pngPaths": [],
      "id": 20
    },
    {
      "originalProjectId": 2,
      "decay": 0,
      "loopStartTime": 0,
      "originalLoopStartTime": -1,
      "originalScale": 0,
      "filePath": "/home/timfitzgerald/stemmy/stemmy-common/fileStore/p2-9.aiff",
      "source": 2,
      "pngPaths": [],
      "id": 21
    },
    {
      "originalProjectId": 2,
      "decay": 0,
      "loopStartTime": 0,
      "originalLoopStartTime": -1,
      "originalScale": 0,
      "filePath": "/home/timfitzgerald/stemmy/stemmy-common/fileStore/p2-11.aiff",
      "source": 2,
      "pngPaths": [],
      "id": 22
    },
    {
      "originalProjectId": 2,
      "decay": 0,
      "loopStartTime": 0,
      "originalLoopStartTime": -1,
      "originalScale": 0,
      "filePath": "/home/timfitzgerald/stemmy/stemmy-common/fileStore/p2-10.aiff",
      "source": 2,
      "pngPaths": [],
      "id": 23
    },
    {
      "originalProjectId": 2,
      "decay": 0,
      "loopStartTime": 0,
      "originalLoopStartTime": -1,
      "originalScale": 0,
      "filePath": "/home/timfitzgerald/stemmy/stemmy-common/fileStore/p2-1.aiff",
      "source": 2,
      "pngPaths": [],
      "id": 24
    },
    {
      "originalProjectId": 3,
      "decay": 0,
      "loopStartTime": 0,
      "originalLoopStartTime": -1,
      "originalScale": 0,
      "filePath": "/home/timfitzgerald/stemmy/stemmy-common/fileStore/p3-2.aiff",
      "source": 2,
      "pngPaths": [],
      "id": 25
    },
    {
      "originalProjectId": 3,
      "decay": 0,
      "loopStartTime": 0,
      "originalLoopStartTime": -1,
      "originalScale": 0,
      "filePath": "/home/timfitzgerald/stemmy/stemmy-common/fileStore/p3-4.aiff",
      "source": 2,
      "pngPaths": [],
      "id": 26
    },
    {
      "originalProjectId": 3,
      "decay": 0,
      "loopStartTime": 0,
      "originalLoopStartTime": -1,
      "originalScale": 0,
      "filePath": "/home/timfitzgerald/stemmy/stemmy-common/fileStore/p3-3.aiff",
      "source": 2,
      "pngPaths": [],
      "id": 27
    },
    {
      "originalProjectId": 3,
      "decay": 0,
      "loopStartTime": 0,
      "originalLoopStartTime": -1,
      "originalScale": 0,
      "filePath": "/home/timfitzgerald/stemmy/stemmy-common/fileStore/p3-0.aiff",
      "source": 2,
      "pngPaths": [],
      "id": 28
    },
    {
      "originalProjectId": 3,
      "decay": 0,
      "loopStartTime": 0,
      "originalLoopStartTime": -1,
      "originalScale": 0,
      "filePath": "/home/timfitzgerald/stemmy/stemmy-common/fileStore/p3-6.aiff",
      "source": 2,
      "pngPaths": [],
      "id": 29
    },
    {
      "originalProjectId": 3,
      "decay": 0,
      "loopStartTime": 0,
      "originalLoopStartTime": -1,
      "originalScale": 0,
      "filePath": "/home/timfitzgerald/stemmy/stemmy-common/fileStore/p3-7.aiff",
      "source": 2,
      "pngPaths": [],
      "id": 30
    },
    {
      "originalProjectId": 3,
      "decay": 0,
      "loopStartTime": 0,
      "originalLoopStartTime": -1,
      "originalScale": 0,
      "filePath": "/home/timfitzgerald/stemmy/stemmy-common/fileStore/p3-8.aiff",
      "source": 2,
      "pngPaths": [],
      "id": 31
    },
    {
      "originalProjectId": 3,
      "decay": 0,
      "loopStartTime": 0,
      "originalLoopStartTime": -1,
      "originalScale": 0,
      "filePath": "/home/timfitzgerald/stemmy/stemmy-common/fileStore/p3-5.aiff",
      "source": 2,
      "pngPaths": [],
      "id": 32
    },
    {
      "originalProjectId": 3,
      "decay": 0,
      "loopStartTime": 0,
      "originalLoopStartTime": -1,
      "originalScale": 0,
      "filePath": "/home/timfitzgerald/stemmy/stemmy-common/fileStore/p3-9.aiff",
      "source": 2,
      "pngPaths": [],
      "id": 33
    },
    {
      "originalProjectId": 3,
      "decay": 0,
      "loopStartTime": 0,
      "originalLoopStartTime": -1,
      "originalScale": 0,
      "filePath": "/home/timfitzgerald/stemmy/stemmy-common/fileStore/p3-10.aiff",
      "source": 2,
      "pngPaths": [],
      "id": 34
    },
    {
      "originalProjectId": 3,
      "decay": 0,
      "loopStartTime": 0,
      "originalLoopStartTime": -1,
      "originalScale": 0,
      "filePath": "/home/timfitzgerald/stemmy/stemmy-common/fileStore/p3-11.aiff",
      "source": 2,
      "pngPaths": [],
      "id": 35
    },
    {
      "originalProjectId": 3,
      "decay": 0,
      "loopStartTime": 0,
      "originalLoopStartTime": -1,
      "originalScale": 0,
      "filePath": "/home/timfitzgerald/stemmy/stemmy-common/fileStore/p3-1.aiff",
      "source": 2,
      "pngPaths": [],
      "id": 36
    }
  ]
}